README.md
setup.cfg
setup.py
gamecredits/__init__.py
gamecredits/constants.py
gamecredits/entities.py
gamecredits/factories.py
gamecredits/helpers.py
gamecredits/test_factories.py
gamecredits.egg-info/PKG-INFO
gamecredits.egg-info/SOURCES.txt
gamecredits.egg-info/dependency_links.txt
gamecredits.egg-info/not-zip-safe
gamecredits.egg-info/requires.txt
gamecredits.egg-info/top_level.txt