Metadata-Version: 1.1
Name: gamecredits
Version: 0.1.4
Summary: Tools for working with the GameCredits cryptocurrency
Home-page: https://github.com/gamecredits-project/python-gamecredits
Author: Nikola Divic
Author-email: divicnikola@gmail.com
License: MIT
Download-URL: https://github.com/gamecredits-project/python-gamecredits/archive/0.1.4.tar.gz
Keywords: gamecredits,cryptocurrency,bitcoin
Platform: UNKNOWN
